{
    "entity": "Tesla, Inc.",
    "category": "us-gaap",
    "feature": "NetCashProvidedByUsedInInvestingActivitiesContinuingOperations",
    "unit": "USD",
    "label": "Net Cash Provided by (Used in) Investing Activities, Continuing Operations",
    "description": "Amount of cash inflow (outflow) of investing activities, excluding discontinued operations. Investing activity cash flows include making and collecting loans and acquiring and disposing of debt or equity instruments and property, plant, and equipment and other productive assets.",
    "data": [
        {
            "start": "2012-01-01",
            "end": "2012-12-31",
            "val": -206930000,
            "accn": "0001564590-15-001031",
            "fy": 2014,
            "fp": "FY",
            "form": "10-K",
            "filed": "2015-02-26",
            "frame": "CY2012"
        },
        {
            "start": "2013-01-01",
            "end": "2013-06-30",
            "val": -82410000,
            "accn": "0001193125-14-303175",
            "fy": 2014,
            "fp": "Q2",
            "form": "10-Q",
            "filed": "2014-08-08"
        },
        {
            "start": "2013-01-01",
            "end": "2013-09-30",
            "val": -159912000,
            "accn": "0001193125-14-403635",
            "fy": 2014,
            "fp": "Q3",
            "form": "10-Q",
            "filed": "2014-11-07"
        },
        {
            "start": "2013-01-01",
            "end": "2013-12-31",
            "val": -249417000,
            "accn": "0001564590-16-013195",
            "fy": 2015,
            "fp": "FY",
            "form": "10-K",
            "filed": "2016-02-24",
            "frame": "CY2013"
        },
        {
            "start": "2013-01-01",
            "end": "2013-12-31",
            "val": -249417000,
            "accn": "0001564590-15-001031",
            "fy": 2014,
            "fp": "FY",
            "form": "10-K",
            "filed": "2015-02-26"
        },
        {
            "start": "2014-01-01",
            "end": "2014-03-31",
            "val": -329180000,
            "accn": "0001564590-15-003789",
            "fy": 2015,
            "fp": "Q1",
            "form": "10-Q",
            "filed": "2015-05-11",
            "frame": "CY2014Q1"
        },
        {
            "start": "2014-01-01",
            "end": "2014-06-30",
            "val": -326570000,
            "accn": "0001564590-15-006666",
            "fy": 2015,
            "fp": "Q2",
            "form": "10-Q",
            "filed": "2015-08-07"
        },
        {
            "start": "2014-01-01",
            "end": "2014-06-30",
            "val": -326570000,
            "accn": "0001193125-14-303175",
            "fy": 2014,
            "fp": "Q2",
            "form": "10-Q",
            "filed": "2014-08-08"
        },
        {
            "start": "2014-01-01",
            "end": "2014-09-30",
            "val": -618213000,
            "accn": "0001564590-15-009741",
            "fy": 2015,
            "fp": "Q3",
            "form": "10-Q",
            "filed": "2015-11-05"
        },
        {
            "start": "2014-01-01",
            "end": "2014-09-30",
            "val": -618213000,
            "accn": "0001193125-14-403635",
            "fy": 2014,
            "fp": "Q3",
            "form": "10-Q",
            "filed": "2014-11-07"
        },
        {
            "start": "2014-01-01",
            "end": "2014-12-31",
            "val": -990444000,
            "accn": "0001564590-17-003118",
            "fy": 2016,
            "fp": "FY",
            "form": "10-K",
            "filed": "2017-03-01",
            "frame": "CY2014"
        },
        {
            "start": "2014-01-01",
            "end": "2014-12-31",
            "val": -990444000,
            "accn": "0001564590-16-013195",
            "fy": 2015,
            "fp": "FY",
            "form": "10-K",
            "filed": "2016-02-24"
        },
        {
            "start": "2014-01-01",
            "end": "2014-12-31",
            "val": -990444000,
            "accn": "0001564590-15-001031",
            "fy": 2014,
            "fp": "FY",
            "form": "10-K",
            "filed": "2015-02-26"
        },
        {
            "start": "2015-01-01",
            "end": "2015-03-31",
            "val": -432344000,
            "accn": "0001564590-16-018886",
            "fy": 2016,
            "fp": "Q1",
            "form": "10-Q",
            "filed": "2016-05-10",
            "frame": "CY2015Q1"
        },
        {
            "start": "2015-01-01",
            "end": "2015-03-31",
            "val": -432344000,
            "accn": "0001564590-15-003789",
            "fy": 2015,
            "fp": "Q1",
            "form": "10-Q",
            "filed": "2015-05-11"
        },
        {
            "start": "2015-01-01",
            "end": "2015-06-30",
            "val": -855181000,
            "accn": "0001564590-16-023024",
            "fy": 2016,
            "fp": "Q2",
            "form": "10-Q",
            "filed": "2016-08-05"
        },
        {
            "start": "2015-01-01",
            "end": "2015-06-30",
            "val": -855181000,
            "accn": "0001564590-15-006666",
            "fy": 2015,
            "fp": "Q2",
            "form": "10-Q",
            "filed": "2015-08-07"
        },
        {
            "start": "2015-01-01",
            "end": "2015-09-30",
            "val": -1259271000,
            "accn": "0001564590-16-026820",
            "fy": 2016,
            "fp": "Q3",
            "form": "10-Q",
            "filed": "2016-11-02"
        },
        {
            "start": "2015-01-01",
            "end": "2015-09-30",
            "val": -1259271000,
            "accn": "0001564590-15-009741",
            "fy": 2015,
            "fp": "Q3",
            "form": "10-Q",
            "filed": "2015-11-05"
        },
        {
            "start": "2015-01-01",
            "end": "2015-12-31",
            "val": -1673551000,
            "accn": "0001564590-18-002956",
            "fy": 2017,
            "fp": "FY",
            "form": "10-K",
            "filed": "2018-02-23",
            "frame": "CY2015"
        },
        {
            "start": "2015-01-01",
            "end": "2015-12-31",
            "val": -1673551000,
            "accn": "0001564590-17-003118",
            "fy": 2016,
            "fp": "FY",
            "form": "10-K",
            "filed": "2017-03-01"
        },
        {
            "start": "2015-01-01",
            "end": "2015-12-31",
            "val": -1673551000,
            "accn": "0001564590-16-013195",
            "fy": 2015,
            "fp": "FY",
            "form": "10-K",
            "filed": "2016-02-24"
        },
        {
            "start": "2016-01-01",
            "end": "2016-03-31",
            "val": -233819000,
            "accn": "0001564590-17-009968",
            "fy": 2017,
            "fp": "Q1",
            "form": "10-Q",
            "filed": "2017-05-10",
            "frame": "CY2016Q1"
        },
        {
            "start": "2016-01-01",
            "end": "2016-03-31",
            "val": -233819000,
            "accn": "0001564590-16-018886",
            "fy": 2016,
            "fp": "Q1",
            "form": "10-Q",
            "filed": "2016-05-10"
        },
        {
            "start": "2016-01-01",
            "end": "2016-06-30",
            "val": -553673000,
            "accn": "0001564590-17-015705",
            "fy": 2017,
            "fp": "Q2",
            "form": "10-Q",
            "filed": "2017-08-04"
        },
        {
            "start": "2016-01-01",
            "end": "2016-06-30",
            "val": -553673000,
            "accn": "0001564590-16-023024",
            "fy": 2016,
            "fp": "Q2",
            "form": "10-Q",
            "filed": "2016-08-05"
        },
        {
            "start": "2016-01-01",
            "end": "2016-09-30",
            "val": -821679000,
            "accn": "0001564590-17-021343",
            "fy": 2017,
            "fp": "Q3",
            "form": "10-Q",
            "filed": "2017-11-03"
        },
        {
            "start": "2016-01-01",
            "end": "2016-09-30",
            "val": -821679000,
            "accn": "0001564590-16-026820",
            "fy": 2016,
            "fp": "Q3",
            "form": "10-Q",
            "filed": "2016-11-02"
        },
        {
            "start": "2016-01-01",
            "end": "2016-12-31",
            "val": -1416430000,
            "accn": "0001564590-18-002956",
            "fy": 2017,
            "fp": "FY",
            "form": "10-K",
            "filed": "2018-02-23",
            "frame": "CY2016"
        },
        {
            "start": "2016-01-01",
            "end": "2016-12-31",
            "val": -1416430000,
            "accn": "0001564590-17-003118",
            "fy": 2016,
            "fp": "FY",
            "form": "10-K",
            "filed": "2017-03-01"
        },
        {
            "start": "2017-01-01",
            "end": "2017-03-31",
            "val": -881719000,
            "accn": "0001564590-18-011086",
            "fy": 2018,
            "fp": "Q1",
            "form": "10-Q",
            "filed": "2018-05-07",
            "frame": "CY2017Q1"
        },
        {
            "start": "2017-01-01",
            "end": "2017-03-31",
            "val": -926943000,
            "accn": "0001564590-17-009968",
            "fy": 2017,
            "fp": "Q1",
            "form": "10-Q",
            "filed": "2017-05-10"
        },
        {
            "start": "2017-01-01",
            "end": "2017-06-30",
            "val": -2142159000,
            "accn": "0001564590-17-015705",
            "fy": 2017,
            "fp": "Q2",
            "form": "10-Q",
            "filed": "2017-08-04"
        },
        {
            "start": "2017-01-01",
            "end": "2017-09-30",
            "val": -3457091000,
            "accn": "0001564590-17-021343",
            "fy": 2017,
            "fp": "Q3",
            "form": "10-Q",
            "filed": "2017-11-03"
        },
        {
            "start": "2017-01-01",
            "end": "2017-12-31",
            "val": -4418967000,
            "accn": "0001564590-18-002956",
            "fy": 2017,
            "fp": "FY",
            "form": "10-K",
            "filed": "2018-02-23",
            "frame": "CY2017"
        },
        {
            "start": "2018-01-01",
            "end": "2018-03-31",
            "val": -728637000,
            "accn": "0001564590-18-011086",
            "fy": 2018,
            "fp": "Q1",
            "form": "10-Q",
            "filed": "2018-05-07",
            "frame": "CY2018Q1"
        }
    ]
}