{
    "entity": "Tesla, Inc.",
    "category": "us-gaap",
    "feature": "NotionalAmountOfForeignCurrencyDerivatives",
    "unit": "USD",
    "label": "Notional Amount of Foreign Currency Derivatives (Deprecated 2013-01-31)",
    "description": "Aggregate notional amount of foreign currency exchange rate derivatives. Notional amount refers to the number of currency units specified in the foreign currency derivative contract.",
    "data": [
        {
            "end": "2010-12-31",
            "val": 7200000,
            "accn": "0001193125-12-137560",
            "fy": 2011,
            "fp": "FY",
            "form": "10-K/A",
            "filed": "2012-03-28",
            "frame": "CY2010Q4I"
        },
        {
            "end": "2011-12-31",
            "val": 8800000,
            "accn": "0001193125-13-096241",
            "fy": 2012,
            "fp": "FY",
            "form": "10-K",
            "filed": "2013-03-07",
            "frame": "CY2011Q4I"
        },
        {
            "end": "2011-12-31",
            "val": 8800000,
            "accn": "0001193125-12-457610",
            "fy": 2012,
            "fp": "Q3",
            "form": "10-Q",
            "filed": "2012-11-07"
        },
        {
            "end": "2011-12-31",
            "val": 8800000,
            "accn": "0001193125-12-332138",
            "fy": 2012,
            "fp": "Q2",
            "form": "10-Q",
            "filed": "2012-08-02"
        },
        {
            "end": "2011-12-31",
            "val": 8800000,
            "accn": "0001193125-12-225825",
            "fy": 2012,
            "fp": "Q1",
            "form": "10-Q",
            "filed": "2012-05-10"
        },
        {
            "end": "2011-12-31",
            "val": 8800000,
            "accn": "0001193125-12-137560",
            "fy": 2011,
            "fp": "FY",
            "form": "10-K/A",
            "filed": "2012-03-28"
        },
        {
            "end": "2012-03-31",
            "val": 18300000,
            "accn": "0001193125-12-225825",
            "fy": 2012,
            "fp": "Q1",
            "form": "10-Q",
            "filed": "2012-05-10",
            "frame": "CY2012Q1I"
        },
        {
            "end": "2012-06-30",
            "val": 14100000,
            "accn": "0001193125-12-332138",
            "fy": 2012,
            "fp": "Q2",
            "form": "10-Q",
            "filed": "2012-08-02",
            "frame": "CY2012Q2I"
        },
        {
            "end": "2012-09-30",
            "val": 4900000,
            "accn": "0001193125-12-457610",
            "fy": 2012,
            "fp": "Q3",
            "form": "10-Q",
            "filed": "2012-11-07",
            "frame": "CY2012Q3I"
        }
    ]
}